wildcatter/__init__.py
wildcatter/__main__.py
wildcatter/environment.py
wildcatter/py.typed
wildcatter-0.1.1.dist-info/entry_points.txt
wildcatter-0.1.1.dist-info/LICENSE
wildcatter-0.1.1.dist-info/WHEEL
wildcatter-0.1.1.dist-info/METADATA
wildcatter-0.1.1.dist-info/RECORD
