Metadata-Version: 2.1
Name: wildcatter
Version: 0.1.1
Summary: Wildcatter
Home-page: https://github.com/GeoML-SIG/wildcatter
License: Apache-2.0
Author: Altay Sansal
Author-email: tasansal@users.noreply.github.com
Requires-Python: >=3.8,<3.10
Classifier: Development Status :: 2 - Pre-Alpha
Classifier: License :: OSI Approved :: Apache Software License
Classifier: Programming Language :: Python :: 3
Classifier: Programming Language :: Python :: 3.8
Classifier: Programming Language :: Python :: 3.9
Provides-Extra: hello_world
Requires-Dist: click (>=8.0.4)
Requires-Dist: gym (>=0.21,<0.22)
Requires-Dist: pygame (==2.1.0); extra == "hello_world"
Requires-Dist: pyglet (>=1.5.26,<2.0.0); extra == "hello_world"
Requires-Dist: stable-baselines3 (>=1.6.0,<2.0.0)
Requires-Dist: torch (>=1.12.0,<2.0.0)
Project-URL: Changelog, https://github.com/GeoML-SIG/wildcatter/releases
Project-URL: Documentation, https://wildcatter.readthedocs.io
Project-URL: Repository, https://github.com/GeoML-SIG/wildcatter
